github_deploy/__init__.py
github_deploy/main.py
github_deploy/commands/__init__.py
github_deploy/commands/_constants.py
github_deploy/commands/_http_utils.py
github_deploy/commands/_repo_utils.py
github_deploy/commands/_utils.py
github_deploy/commands/delete.py
github_deploy/commands/upload.py
github_deploy-1.2.0.dist-info/LICENSE
github_deploy-1.2.0.dist-info/METADATA
github_deploy-1.2.0.dist-info/WHEEL
github_deploy-1.2.0.dist-info/entry_points.txt
github_deploy-1.2.0.dist-info/top_level.txt
github_deploy-1.2.0.dist-info/RECORD
