Metadata-Version: 2.1
Name: github-deploy
Version: 1.2.0
Summary: Deploy yaml files to a large number of repositories in seconds.
Home-page: https://github.com/tj-python/github-deploy
Author: Tonye Jack
Author-email: jtonye@ymail.com
License: MIT
Keywords: yaml,deploy,poly repository,github,single configuration
Requires-Python: >=3.7
License-File: LICENSE
Requires-Dist: asyncclick
Requires-Dist: asyncio
Requires-Dist: aiohttp
Requires-Dist: certifi
Requires-Dist: colorama
Requires-Dist: aiofiles
Requires-Dist: anyio
Provides-Extra: deploy
Requires-Dist: bump2version ; extra == 'deploy'
Requires-Dist: readme-renderer[md] ; extra == 'deploy'
